mbonig/cdk_cicd/__init__.py
mbonig/cdk_cicd/py.typed
mbonig/cdk_cicd/_jsii/__init__.py
mbonig/cdk_cicd/_jsii/cdk-cicd@0.1.3.jsii.tgz
mbonig.cdk_cicd-0.1.3.dist-info/METADATA
mbonig.cdk_cicd-0.1.3.dist-info/WHEEL
mbonig.cdk_cicd-0.1.3.dist-info/top_level.txt
mbonig.cdk_cicd-0.1.3.dist-info/RECORD
