Metadata-Version: 2.1
Name: mbonig.cdk-cicd
Version: 0.1.3
Summary: A CDK Construct that creates a CodePipeline that will build and deploy a CDK Stack
Home-page: https://github.com/mbonig/cdk-cicd.git
Author: Matthew Bonig<matthew.bonig@gmail.com>
License: MIT
Project-URL: Source, https://github.com/mbonig/cdk-cicd.git
Platform: UNKNOWN
Classifier: Intended Audience :: Developers
Classifier: Operating System :: OS Independent
Classifier: Programming Language :: JavaScript
Classifier: Programming Language :: Python :: 3 :: Only
Classifier: Programming Language :: Python :: 3.6
Classifier: Programming Language :: Python :: 3.7
Classifier: Programming Language :: Python :: 3.8
Classifier: Typing :: Typed
Classifier: License :: OSI Approved
Requires-Python: >=3.6
Requires-Dist: jsii (~=0.21.1)
Requires-Dist: publication (>=0.0.3)
Requires-Dist: aws-cdk.aws-codebuild (<2.0.0,>=1.20.0)
Requires-Dist: aws-cdk.aws-codepipeline (<2.0.0,>=1.20.0)
Requires-Dist: aws-cdk.aws-codepipeline-actions (<2.0.0,>=1.20.0)
Requires-Dist: aws-cdk.aws-events (<2.0.0,>=1.20.0)
Requires-Dist: aws-cdk.aws-events-targets (<2.0.0,>=1.20.0)
Requires-Dist: aws-cdk.aws-s3 (<2.0.0,>=1.20.0)
Requires-Dist: aws-cdk.core (<2.0.0,>=1.20.0)
